odoo/addons/account_create_tax_cash_basis_entry_hook/README.rst
odoo/addons/account_create_tax_cash_basis_entry_hook/__init__.py
odoo/addons/account_create_tax_cash_basis_entry_hook/__manifest__.py
odoo/addons/account_create_tax_cash_basis_entry_hook/hooks.py
odoo/addons/account_create_tax_cash_basis_entry_hook/i18n/account_create_tax_cash_basis_entry_hook.pot
odoo/addons/account_create_tax_cash_basis_entry_hook/models/__init__.py
odoo/addons/account_create_tax_cash_basis_entry_hook/models/account_move.py
odoo/addons/account_create_tax_cash_basis_entry_hook/readme/CONTRIBUTORS.rst
odoo/addons/account_create_tax_cash_basis_entry_hook/readme/DESCRIPTION.rst
odoo/addons/account_create_tax_cash_basis_entry_hook/readme/USAGE.rst
odoo/addons/account_create_tax_cash_basis_entry_hook/static/description/icon.png
odoo/addons/account_create_tax_cash_basis_entry_hook/static/description/index.html
odoo12_addon_account_create_tax_cash_basis_entry_hook-12.0.1.0.0.99.dev4.dist-info/METADATA
odoo12_addon_account_create_tax_cash_basis_entry_hook-12.0.1.0.0.99.dev4.dist-info/WHEEL
odoo12_addon_account_create_tax_cash_basis_entry_hook-12.0.1.0.0.99.dev4.dist-info/top_level.txt
odoo12_addon_account_create_tax_cash_basis_entry_hook-12.0.1.0.0.99.dev4.dist-info/RECORD
